toml_cfg_tool/__init__.py
toml_cfg_tool/toml_cfg_tool.py
toml_cfg_tool/src/bkup.py
toml_cfg_tool/src/cli.py
toml_cfg_tool/src/color_codes.py
toml_cfg_tool/src/config.py
toml_cfg_tool/src/contrib.py
toml_cfg_tool/src/creation.py
toml_cfg_tool/src/print_colors.py
toml_cfg_tool/src/reader.py
toml_cfg_tool/src/updates_cfg.py
toml_cfg_tool/src/updates_toml.py
toml_cfg_tool/src/github_workflows/version_checker.py
toml_cfg_tool-0.0.9.dist-info/METADATA
toml_cfg_tool-0.0.9.dist-info/WHEEL
toml_cfg_tool-0.0.9.dist-info/entry_points.txt
toml_cfg_tool-0.0.9.dist-info/top_level.txt
toml_cfg_tool-0.0.9.dist-info/RECORD
