Metadata-Version: 2.1
Name: toml_cfg_tool
Version: 0.0.9
Summary: Never gonna give you up!
Home-page: https://github.com/VinnyVanGogh/toml_cfg_tool.git
Author: VinnyVanGogh
Author-email: VinnyVanGogh <computerscience@vinny-van-gogh.com>
License: MIT
Project-URL: Homepage, https://github.com/VinnyVanGogh/toml_cfg_tool.git
Requires-Python: >=3.10
